mlb_showdown_bot/__init__.py
mlb_showdown_bot/__main__.py
mlb_showdown_bot/baseball_ref_scraper.py
mlb_showdown_bot/firebase.py
mlb_showdown_bot/nicknames.csv
mlb_showdown_bot/player_ids.csv
mlb_showdown_bot/postgres_db.py
mlb_showdown_bot/showdown_constants.py
mlb_showdown_bot/showdown_player_card.py
mlb_showdown_bot/version.py
mlb_showdown_bot/wotc_player_cards.py
mlb_showdown_bot/cache_data/.gitkeep
mlb_showdown_bot/card_art/.DS_Store
mlb_showdown_bot/card_art/2001-BLACK-LINES.png
mlb_showdown_bot/card_art/2001-WHITE-LINES.png
mlb_showdown_bot/card_art/ASG-2023-BG-AL.png
mlb_showdown_bot/card_art/ASG-2023-BG-NL.png
mlb_showdown_bot/card_art/ASG-2023-FG.png
mlb_showdown_bot/card_art/ASG-2024-BAR-1.png
mlb_showdown_bot/card_art/ASG-2024-BAR-2.png
mlb_showdown_bot/card_art/ASG-2024-BG-AL.png
mlb_showdown_bot/card_art/ASG-2024-BG-NL.png
mlb_showdown_bot/card_art/ASG-2024-BOTTOM-COLOR.png
mlb_showdown_bot/card_art/ASG-2024-STAR.png
mlb_showdown_bot/card_art/ASG-2024-TEXAS-TEXT.png
mlb_showdown_bot/card_art/BLACK_CIRCLE.png
mlb_showdown_bot/card_art/COMIC_BOOK_LINES.png
mlb_showdown_bot/card_art/COOPERSTOWN.png
mlb_showdown_bot/card_art/DARK-GRADIENT.png
mlb_showdown_bot/card_art/DARKENER.png
mlb_showdown_bot/card_art/ELLIPSE-LARGE.png
mlb_showdown_bot/card_art/ELLIPSE-MEDIUM.png
mlb_showdown_bot/card_art/ELLIPSE-SMALL.png
mlb_showdown_bot/card_art/FLAMES.png
mlb_showdown_bot/card_art/GALAXY.png
mlb_showdown_bot/card_art/GOLD.png
mlb_showdown_bot/card_art/GOLD_FRAME.png
mlb_showdown_bot/card_art/GOLD_RUSH.png
mlb_showdown_bot/card_art/LIGHT-GRADIENT.png
mlb_showdown_bot/card_art/MOONLIGHT.png
mlb_showdown_bot/card_art/RADIAL.png
mlb_showdown_bot/card_art/RAINBOW-FOIL.png
mlb_showdown_bot/card_art/SAPPHIRE.png
mlb_showdown_bot/card_art/SUPER SEASON.png
mlb_showdown_bot/card_art/WHITE_CIRCLE.png
mlb_showdown_bot/card_art/WHITE_SMOKE.png
mlb_showdown_bot/classes/accolade.py
mlb_showdown_bot/classes/chart.py
mlb_showdown_bot/classes/colors.py
mlb_showdown_bot-3.9.3.dist-info/LICENSE
mlb_showdown_bot-3.9.3.dist-info/METADATA
mlb_showdown_bot-3.9.3.dist-info/WHEEL
mlb_showdown_bot-3.9.3.dist-info/entry_points.txt
mlb_showdown_bot-3.9.3.dist-info/top_level.txt
mlb_showdown_bot-3.9.3.dist-info/RECORD
