Metadata-Version: 2.1
Name: mlb-showdown-bot
Version: 3.9.3
Summary: Create custom MLB Showdown cards
Home-page: https://github.com/mgula57/mlb_showdown_card_bot
Author: Matthew Gula
Author-email: mlbshowdownbot@gmail.com
License: Unlicense
Classifier: License :: OSI Approved :: The Unlicense (Unlicense)
Classifier: Programming Language :: Python :: 3.7
Classifier: Programming Language :: Python :: 3.8
Requires-Python: >=3.7
License-File: LICENSE
Requires-Dist: aenum >=3.1.15
Requires-Dist: apiclient >=1.0.4
Requires-Dist: beautifulsoup4 >=4.9.3
Requires-Dist: bs4 >=0.0.1
Requires-Dist: firebase-admin >=6.0.1
Requires-Dist: google >=3.0.0
Requires-Dist: google-api-python-client >=2.7.0
Requires-Dist: lxml >=4.6.1
Requires-Dist: numpy >=1.19.4
Requires-Dist: oauth2client >=4.1.3
Requires-Dist: pandas >=1.1.4
Requires-Dist: Pillow >=7.2.0
Requires-Dist: pydantic >=2.4.2
Requires-Dist: requests >=2.25.0
Requires-Dist: simplejson >=3.17.6
Requires-Dist: Unidecode ==1.2.0
Requires-Dist: urllib3 >=1.26.2
Requires-Dist: webcolors >=1.13
Requires-Dist: xlrd >=1.2.0
